setup.py
bno_probability/Binomialdistribution.py
bno_probability/Gaussiandistribution.py
bno_probability/Generaldistribution.py
bno_probability/__init__.py
bno_probability.egg-info/PKG-INFO
bno_probability.egg-info/SOURCES.txt
bno_probability.egg-info/dependency_links.txt
bno_probability.egg-info/not-zip-safe
bno_probability.egg-info/top_level.txt